AutoTrackers/AutoTrackers.py
AutoTrackers/__init__.py
AutoTrackers/torrent.py
AutoTrackers/tracker_list.py
AutoTrackers/bencode/BTL.py
AutoTrackers/bencode/__init__.py
AutoTrackers/bencode/exceptions.py
AutoTrackers-1.0.1.dist-info/LICENSE
AutoTrackers-1.0.1.dist-info/METADATA
AutoTrackers-1.0.1.dist-info/WHEEL
AutoTrackers-1.0.1.dist-info/top_level.txt
AutoTrackers-1.0.1.dist-info/RECORD
