Metadata-Version: 2.1
Name: AutoTrackers
Version: 1.0.1
Summary: 为 torrent 文件增加 Tracker 地址
Home-page: https://github.com/zaw007/AutoTrackers
Author: zaw
Author-email: zhangqishao007@foxmail.com
License: LGPL
Platform: UNKNOWN
